MANIFEST.in
README.md
setup.cfg
setup.py
geoviz/__init__.py
geoviz/choropleth.py
geoviz/params.py
geoviz/preprocess.py
geoviz.egg-info/PKG-INFO
geoviz.egg-info/SOURCES.txt
geoviz.egg-info/dependency_links.txt
geoviz.egg-info/requires.txt
geoviz.egg-info/top_level.txt
geoviz/data/__init__.py
geoviz/data/counties-albers-10m.json
geoviz/data/omb_msa_1990_2018.csv
geoviz/data/omb_msa_2017.csv
geoviz/data/states-albers-10m.json
geoviz/data/us-albers-counties.json.txt
geoviz/data/us-albers.json.txt