Metadata-Version: 2.1
Name: geoviz
Version: 1.0.1
Summary: Wrapper to easily make geo-based visualizations
Home-page: https://github.com/LocusAnalytics/geoviz
Author: W. Aaron Lee
Author-email: alee@locus.co
License: MIT
Platform: UNKNOWN
